biobb_3dshaper/__init__.py
biobb_3dshaper/dshaper/__init__.py
biobb_3dshaper/dshaper/model.py
biobb_3dshaper/dshaper/parsesai.py
biobb_3dshaper/test/__init__.py
biobb_morphIVD/__init__.py
biobb_morphIVD/biobb_morphIVD.py
biobb_morphIVD/biobb_morphIVD_main.py
biobb_morphIVD/complete_workflow.py
biobb_morphIVD/sai_workflow.py
biobb_morphIVD/workflow.py
biobb_morphIVD/biobb_morphIVD/__init__.py
biobb_morphIVD/biobb_morphIVD/biobb_morphIVD.py
biobb_morphIVD/biobb_morphIVD/common.py
biobb_morphIVD/biobb_morphIVD/morph.py
biobb_morphIVD/morphIVD/__init__.py
biobb_morphIVD/morphIVD/common.py
biobb_morphIVD/morphIVD/model.py
biobb_morphIVD/morphIVD/morph.py
biobb_morphIVD/test/__init__.py
biobb_morphIVD-1.5.dist-info/LICENSE
biobb_morphIVD-1.5.dist-info/METADATA
biobb_morphIVD-1.5.dist-info/WHEEL
biobb_morphIVD-1.5.dist-info/top_level.txt
biobb_morphIVD-1.5.dist-info/RECORD
