Metadata-Version: 2.1
Name: biobb-morphIVD
Version: 1.5
Summary: Biobb_3DShaper is use case to run a simulation with Abaqus.
Home-page: https://github.com/mapoferri/Biobb_MorphIVD
Author: Biobb developers - Maria Paola Ferri
Author-email: maria.ferri@bsc.es
License: UNKNOWN
Project-URL: Documentation, http://biobb_template.readthedocs.io/en/latest/
Project-URL: Bioexcel, https://bioexcel.eu/
Keywords: Bioinformatics Workflows BioExcel Compatibility
Platform: UNKNOWN
Classifier: Development Status :: 3 - Alpha
Classifier: Programming Language :: Python :: 3.8
Classifier: License :: OSI Approved :: Apache Software License
Classifier: Operating System :: MacOS :: MacOS X
Classifier: Operating System :: POSIX
Requires-Python: ==3.8.*
License-File: LICENSE
Requires-Dist: biobb-common (==3.7.0)
Requires-Dist: biobb-md (>=3.7.0)
Requires-Dist: biobb-analysis (==3.7.0)
